spec_mock/__init__.py
spec_mock/ast_traverser.py
spec_mock/get_signatures.py
spec_mock/implementation.py
spec_mock/spec_mock.py
spec_mock/utils.py
spec_mock-1.0.1.dist-info/METADATA
spec_mock-1.0.1.dist-info/WHEEL
spec_mock-1.0.1.dist-info/top_level.txt
spec_mock-1.0.1.dist-info/RECORD
