Metadata-Version: 2.1
Name: spec_mock
Version: 1.0.1
Summary: Powerful mocks with complete specs
Home-page: https://github.com/AharonSambol/spec_mock
Author: Aharon Sambol
Author-email: aharon.sambol@gmail.com
License: MIT License
Keywords: mock,spec,test
